do/__init__.py
donetools/__init__.py
donetools/info.py
donetools/json.py
donetools/path.py
donetools-0.0.29.dist-info/LICENSE
donetools-0.0.29.dist-info/METADATA
donetools-0.0.29.dist-info/WHEEL
donetools-0.0.29.dist-info/top_level.txt
donetools-0.0.29.dist-info/RECORD
