Metadata-Version: 2.1
Name: donetools
Version: 0.0.29
Summary: Done utilities in Python.
Author-email: Ding Yi <loongdone@gmail.com>
License: MIT License
Project-URL: Homepage, https://github.com/onedonedone/Python-Tools
Project-URL: Repository, https://github.com/onedonedone/Python-Tools
License-File: LICENSE
